dac_autoreg/__init__.py
dac_autoreg/modules.py
dac_autoreg-0.3.0.dist-info/LICENSE
dac_autoreg-0.3.0.dist-info/METADATA
dac_autoreg-0.3.0.dist-info/WHEEL
dac_autoreg-0.3.0.dist-info/top_level.txt
dac_autoreg-0.3.0.dist-info/RECORD
